README.md
setup.py
simplines/__init__.py
simplines/api.py
simplines/bsplines.py
simplines/cad.py
simplines/gallery.py
simplines/linalg.py
simplines/quadratures.py
simplines/spaces.py
simplines/utilities.py
simplines/version.py
simplines.egg-info/PKG-INFO
simplines.egg-info/SOURCES.txt
simplines.egg-info/dependency_links.txt
simplines.egg-info/requires.txt
simplines.egg-info/top_level.txt