Metadata-Version: 1.0
Name: simplines
Version: 0.1
Summary: TODO.
Home-page: https://github.com/ratnania/simplines
Author: Ahmed RATNANI
Author-email: ratnaniahmed@gmail.com
License: LICENSE
Keywords: math
Platform: UNKNOWN
